nrresqml/VERSION.txt
nrresqml/__init__.py
nrresqml/__main__.py
nrresqml/api.py
nrresqml/reporting.py
nrresqml/resqml.py
nrresqml/derivatives/__init__.py
nrresqml/derivatives/dataextraction.py
nrresqml/derivatives/hdf5resqmladaptor.py
nrresqml/derivatives/ijkgridcreator.py
nrresqml/derivatives/rqbuilder.py
nrresqml/derivatives/utils.py
nrresqml/factories/__init__.py
nrresqml/factories/energetics.py
nrresqml/factories/resqml/__init__.py
nrresqml/factories/resqml/common.py
nrresqml/factories/resqml/properties.py
nrresqml/factories/resqml/relationships.py
nrresqml/factories/resqml/representations.py
nrresqml/serialization/__init__.py
nrresqml/serialization/elementify.py
nrresqml/serialization/objectify.py
nrresqml/serialization/postprocessing.py
nrresqml/structures/__init__.py
nrresqml/structures/contenttypes.py
nrresqml/structures/core.py
nrresqml/structures/energetics.py
nrresqml/structures/relationships.py
nrresqml/structures/xsd.py
nrresqml/structures/resqml/__init__.py
nrresqml/structures/resqml/_rqtools.py
nrresqml/structures/resqml/common.py
nrresqml/structures/resqml/geometry.py
nrresqml/structures/resqml/properties.py
nrresqml/structures/resqml/representations.py
nrresqml-1.0.dist-info/LICENSE
nrresqml-1.0.dist-info/METADATA
nrresqml-1.0.dist-info/WHEEL
nrresqml-1.0.dist-info/top_level.txt
nrresqml-1.0.dist-info/RECORD
