Metadata-Version: 2.1
Name: nrresqml
Version: 1.0
Summary: Package for converting Delft3D output to ResQml
Home-page: https://github.com/NorskRegnesentral/nrresqml
Author: Norwegian Computing Center
License: GPL-3.0
Platform: UNKNOWN
Classifier: Programming Language :: Python :: 3
Classifier: Programming Language :: Python :: 3.7
Classifier: License :: OSI Approved :: GNU General Public License v3 (GPLv3)
Classifier: Operating System :: OS Independent
Requires-Python: >=3.7
